flatqube/__init__.py
flatqube/__main__.py
flatqube/cli.py
flatqube/client.py
flatqube/config.py
flatqube/config.yaml
flatqube/constants.py
flatqube/fmt.py
flatqube/models.py
flatqube/version.py
flatqube_client-0.2.4.dist-info/entry_points.txt
flatqube_client-0.2.4.dist-info/LICENSE
flatqube_client-0.2.4.dist-info/WHEEL
flatqube_client-0.2.4.dist-info/METADATA
flatqube_client-0.2.4.dist-info/RECORD
