Metadata-Version: 2.1
Name: flatqube-client
Version: 0.2.4
Summary: FlatQube API client library and CLI tools
License: MIT
Author: Evgeny Prilepin
Author-email: esp.home@gmail.com
Requires-Python: >=3.9,<4.0
Classifier: License :: OSI Approved :: MIT License
Classifier: Programming Language :: Python :: 3
Classifier: Programming Language :: Python :: 3.10
Classifier: Programming Language :: Python :: 3.9
Requires-Dist: appdirs (>=1.4.4,<2.0.0)
Requires-Dist: click (>=8.1.2,<9.0.0)
Requires-Dist: humanize (>=4.0.0,<5.0.0)
Requires-Dist: omegaconf (>=2.2.0,<3.0.0)
Requires-Dist: pydantic (>=1.9.0,<2.0.0)
Requires-Dist: requests (>=2.27.1,<3.0.0)
Requires-Dist: rich (>=12.3.0,<13.0.0)
